mcp_builder/__init__.py
mcp_builder/config.py
mcp_builder/exceptions.py
mcp_builder/generator.py
mcp_builder/validators.py
mcp_builder/cli/__init__.py
mcp_builder/cli/main.py
mcp_builder/cli/prompts.py
mcp_builder/cli/utils.py
mcp_builder/cli/commands/__init__.py
mcp_builder/cli/commands/create.py
mcp_builder/cli/commands/example.py
mcp_builder/cli/commands/init.py
mcp_builder/cli/commands/list.py
mcp_builder/cli/commands/validate.py
mcp_builder/templates/base/.env.example.j2
mcp_builder/templates/base/.gitignore.j2
mcp_builder/templates/base/.pre-commit-config.yaml.j2
mcp_builder/templates/base/Makefile.j2
mcp_builder/templates/base/README.md.j2
mcp_builder/templates/base/pyproject.toml.j2
mcp_builder/templates/docker/.dockerignore.j2
mcp_builder/templates/docker/Dockerfile.j2
mcp_builder/templates/docker/docker-compose.yml.j2
mcp_builder/templates/docs/CONTRIBUTING.md.j2
mcp_builder/templates/docs/api.md.j2
mcp_builder/templates/docs/usage.md.j2
mcp_builder/templates/github/workflows/ci.yml.j2
mcp_builder/templates/licenses/mit.j2
mcp_builder/templates/src/__init__.py.j2
mcp_builder/templates/src/__main__.py.j2
mcp_builder/templates/src/config.py.j2
mcp_builder/templates/src/server.py.j2
mcp_builder/templates/tests/__init__.py.j2
mcp_builder/templates/tests/conftest.py.j2
mcp_builder/templates/tests/test_server.py.j2
mcp_builder/templates/tools/api_tools.py.j2
mcp_builder/templates/tools/custom_tools.py.j2
mcp_builder/templates/tools/data_tools.py.j2
mcp_builder/templates/tools/database_tools.py.j2
mcp_builder/templates/tools/file_tools.py.j2
mcp_builder/templates/tools/genai_tools.py.j2
mcp_builder/templates/tools/rag_tools.py.j2
mcp_builder/templates/tools/web_tools.py.j2
mcp_builder/templates/vscode/extensions.json.j2
mcp_builder/templates/vscode/settings.json.j2
mcp_builder_templates-0.1.0.dist-info/METADATA
mcp_builder_templates-0.1.0.dist-info/WHEEL
mcp_builder_templates-0.1.0.dist-info/entry_points.txt
mcp_builder_templates-0.1.0.dist-info/RECORD
